detect/__init__.py
detect/detect_face.py
pydata_vision-0.0.1.dist-info/LICENSE
pydata_vision-0.0.1.dist-info/METADATA
pydata_vision-0.0.1.dist-info/WHEEL
pydata_vision-0.0.1.dist-info/top_level.txt
pydata_vision-0.0.1.dist-info/RECORD
