Metadata-Version: 2.1
Name: pydata-vision
Version: 0.0.1
Summary: A basic detect package
Home-page: UNKNOWN
Author: Data Vision (Maruf Ibragimov)
Author-email: ifacevision@gmail.com
License: UNKNOWN
Keywords: python,image,detect,face
Platform: UNKNOWN
Classifier: Intended Audience :: Developers
Classifier: Programming Language :: Python :: 3
Classifier: Operating System :: Microsoft :: Windows
License-File: LICENSE
Requires-Dist: opencv-python
Requires-Dist: face-recognition
